printover/__init__.py
printover/overprint.py
printover-1.1.1.dist-info/METADATA
printover-1.1.1.dist-info/WHEEL
printover-1.1.1.dist-info/licenses/LICENSE
printover-1.1.1.dist-info/RECORD
